{
  "version": "6.3.1",
  "flags": {},
  "shapes": [
    {
      "label": "walkable",
      "points": [
        [
          380.83333333333326,
          1072.2916666666667
        ],
        [
          501.66666666666663,
          851.4583333333333
        ],
        [
          139.16666666666657,
          838.9583333333333
        ],
        [
          284.99999999999994,
          759.7916666666666
        ],
        [
          951.6666666666666,
          776.4583333333333
        ],
        [
          1049.5833333333333,
          1070.2083333333333
        ],
        [
          401.66666666666663,
          1076.4583333333333
        ]
      ],
      "group_id": null,
      "description": "",
      "shape_type": "polygon",
      "flags": {},
      "mask": null
    }
  ],
  "imagePath": "train_00030.jpg",
  "imageData": null,
  "imageHeight": 1080,
  "imageWidth": 1920
}